pohoda/Pohoda.py
pohoda/__init__.py
pohoda/entity/ActionPrice.py
pohoda/entity/Addressbook.py
pohoda/entity/Agenda.py
pohoda/entity/CashSlip.py
pohoda/entity/Category.py
pohoda/entity/Contract.py
pohoda/entity/Document.py
pohoda/entity/IndividualPrice.py
pohoda/entity/IntDoc.py
pohoda/entity/IntParam.py
pohoda/entity/Invoice.py
pohoda/entity/IssueSlip.py
pohoda/entity/ListRequest.py
pohoda/entity/Offer.py
pohoda/entity/Order.py
pohoda/entity/PrintRequest.py
pohoda/entity/Receipt.py
pohoda/entity/Stock.py
pohoda/entity/StockTransfer.py
pohoda/entity/Storage.py
pohoda/entity/UserList.py
pohoda/entity/__init__.py
pohoda/entity/addressbook/Header.py
pohoda/entity/addressbook/__init__.py
pohoda/entity/cash_slip/Header.py
pohoda/entity/cash_slip/Item.py
pohoda/entity/cash_slip/Summary.py
pohoda/entity/cash_slip/__init__.py
pohoda/entity/common/AddActionTypeTrait.py
pohoda/entity/common/AddParameterToHeaderTrait.py
pohoda/entity/common/AddParameterTrait.py
pohoda/entity/common/SetNamespaceTrait.py
pohoda/entity/common/SetNodeNameTrait.py
pohoda/entity/common/Trait.py
pohoda/entity/common/__init__.py
pohoda/entity/contract/Desc.py
pohoda/entity/contract/__init__.py
pohoda/entity/document/Header.py
pohoda/entity/document/Item.py
pohoda/entity/document/Part.py
pohoda/entity/document/Summary.py
pohoda/entity/document/__init__.py
pohoda/entity/int_doc/Header.py
pohoda/entity/int_doc/Item.py
pohoda/entity/int_doc/Summary.py
pohoda/entity/int_doc/__init__.py
pohoda/entity/int_param/Settings.py
pohoda/entity/int_param/__init__.py
pohoda/entity/invoice/AdvancePaymentItem.py
pohoda/entity/invoice/Header.py
pohoda/entity/invoice/Item.py
pohoda/entity/invoice/Summary.py
pohoda/entity/invoice/__init__.py
pohoda/entity/issue_slip/Header.py
pohoda/entity/issue_slip/Item.py
pohoda/entity/issue_slip/Summary.py
pohoda/entity/issue_slip/__init__.py
pohoda/entity/list_request/Filter.py
pohoda/entity/list_request/UserFilterName.py
pohoda/entity/list_request/__init__.py
pohoda-1.17.3.dist-info/LICENSE
pohoda-1.17.3.dist-info/METADATA
pohoda-1.17.3.dist-info/WHEEL
pohoda-1.17.3.dist-info/top_level.txt
pohoda-1.17.3.dist-info/RECORD
